flask_tjfu_body/__init__.py
flask_tjfu_body/flask_tjfu_body.py
flask_tjfu_body-1.0.0.dist-info/METADATA
flask_tjfu_body-1.0.0.dist-info/WHEEL
flask_tjfu_body-1.0.0.dist-info/top_level.txt
flask_tjfu_body-1.0.0.dist-info/RECORD
