Metadata-Version: 2.1
Name: flask-tjfu-body
Version: 1.0.0
Home-page: https://github.com/duynguyen02/flask-tjfu-body
Author: duynguyen02
Keywords: Python,Flask
Classifier: Intended Audience :: Developers
Classifier: License :: OSI Approved :: MIT License
Classifier: Programming Language :: Python
Classifier: Operating System :: OS Independent
Requires-Dist: Flask
